quiltz/__init__.py
quiltz/messaging/__init__.py
quiltz/messaging/messenger.py
quiltz/messaging/version.py
quiltz/messaging/engine/__init__.py
quiltz/messaging/engine/smtp.py
quiltz_messaging-0.3.3.dist-info/LICENSE
quiltz_messaging-0.3.3.dist-info/METADATA
quiltz_messaging-0.3.3.dist-info/WHEEL
quiltz_messaging-0.3.3.dist-info/top_level.txt
quiltz_messaging-0.3.3.dist-info/RECORD
