Metadata-Version: 2.1
Name: quiltz-messaging
Version: 0.3.3
Summary: A messaging utility module for python
Home-page: https://github.com/qwaneu/quiltz-messaging
Author: Rob Westgeest
Author-email: rob@qwan.eu
Classifier: Programming Language :: Python :: 3
Classifier: License :: OSI Approved :: MIT License
Classifier: Operating System :: OS Independent
License-File: LICENSE
Requires-Dist: quiltz-domain (<1.0.0,>=0.7.0)
